README.md
setup.cfg
setup.py
cocotbext/jtag/__init__.py
cocotbext/jtag/clkreset.py
cocotbext/jtag/cocotbext_logger.py
cocotbext/jtag/gatedclock.py
cocotbext/jtag/jtag_bus.py
cocotbext/jtag/jtag_device.py
cocotbext/jtag/jtag_driver.py
cocotbext/jtag/jtag_monitor.py
cocotbext/jtag/jtag_sm.py
cocotbext/jtag/ocd_client.py
cocotbext/jtag/version.py
cocotbext/jtag/devices/H3JTAGDevice.py
cocotbext/jtag/devices/M3JTAGDevice.py
cocotbext_jtag.egg-info/PKG-INFO
cocotbext_jtag.egg-info/SOURCES.txt
cocotbext_jtag.egg-info/dependency_links.txt
cocotbext_jtag.egg-info/requires.txt
cocotbext_jtag.egg-info/top_level.txt