Metadata-Version: 2.1
Name: cocotbext-jtag
Version: 0.1.1
Summary: jtag modules for cocotb
Home-page: https://github.com/daxzio/cocotbext-jtag
Download-URL: https://github.com/daxzio/cocotbext-jtag/tarball/master
Author: Dave Keeshan
Author-email: dave.keeshan@daxzio.com
License: MIT
Project-URL: Bug Tracker, https://github.com/daxzio/cocotbext-jtag/issues
Project-URL: Source Code, https://github.com/daxzio/cocotbext-jtag
Keywords: jtag,cocotb
Platform: any
Classifier: Development Status :: 3 - Alpha
Classifier: Framework :: cocotb
Classifier: License :: OSI Approved :: MIT License
Classifier: Operating System :: OS Independent
Classifier: Programming Language :: Python :: 3
Classifier: Topic :: Scientific/Engineering :: Electronic Design Automation (EDA)
Requires-Python: >=3.8
Provides-Extra: test
